deepsleep/__init__.py
deepsleep/utils.py
deepsleep/configs/__init__.py
deepsleep/configs/constants.py
deepsleep/data/__init__.py
deepsleep/data/base_loader.py
deepsleep/data/utils.py
deepsleep/data/dataloaders/__init__.py
deepsleep/data/dataloaders/caro_data.py
deepsleep/data/dataloaders/production_data.py
deepsleep/data/dataloaders/spindle_data.py
deepsleep/data/preproc/__init__.py
deepsleep/data/preproc/linus_preproc.py
deepsleep/data/preproc/linus_preproc_with_filtering.py
deepsleep/data/preproc/new_preproc.py
deepsleep/data/preproc/normed_spindle_preproc.py
deepsleep/data/preproc/spindle_preproc.py
deepsleep/data/preproc/spindle_with_eog_preproc.py
deepsleep/models/__init__.py
deepsleep/models/base_model.py
deepsleep/models/sleep_artefact.py
deepsleep/models/sleep_resnet_3.py
deepsleep/models/sleep_resnet_5.py
deepsleep/models/spindle_human_sleepstage.py
deepsleep/models/spindle_model.py
deepsleep/models/spindle_predict_model.py
deepsleep/models/spindle_sleepstage.py
deepsleep/models/utils.py
deepsleep/models/graphs/__init__.py
deepsleep/models/graphs/spindle_graph.py
deepsleep-1.0.3.data/scripts/predict.py
deepsleep-1.0.3.dist-info/LICENSE
deepsleep-1.0.3.dist-info/METADATA
deepsleep-1.0.3.dist-info/WHEEL
deepsleep-1.0.3.dist-info/top_level.txt
deepsleep-1.0.3.dist-info/RECORD
