Metadata-Version: 2.1
Name: deepsleep
Version: 1.0.3
Summary: Sleep EEG classification
Home-page: https://sleeplearning.ethz.ch
Author: Ami Beuret
Author-email: amibeuret@gmail.com
Classifier: Programming Language :: Python :: 3
Classifier: License :: OSI Approved :: GNU General Public License v3 (GPLv3)
Classifier: Operating System :: OS Independent
Requires-Python: >=3.6
License-File: LICENSE
Requires-Dist: torch ==1.6.0
Requires-Dist: numpy ==1.18.1
Requires-Dist: pandas ==0.25.3
Requires-Dist: Pillow ==6.2.2
Requires-Dist: scipy ==1.4.1
Requires-Dist: sklearn ==0.0
Requires-Dist: torchvision ==0.7.0
Requires-Dist: matplotlib ==3.1.2
Requires-Dist: mne ==0.19.2
Requires-Dist: pyEDFlib ==0.1.22
Requires-Dist: PyYAML ==5.3
Requires-Dist: h5py ==2.10.0
Requires-Dist: mlflow ==1.5.0
Requires-Dist: hmmlearn ==0.2.3
